tuiargs/__init__.py
tuiargs/lib.py
tuiargs/_internal/components.py
tuiargs-0.9.0.dist-info/METADATA
tuiargs-0.9.0.dist-info/WHEEL
tuiargs-0.9.0.dist-info/licenses/LICENSE
tuiargs-0.9.0.dist-info/RECORD
