Metadata-Version: 2.4
Name: tuiargs
Version: 0.9.0
Summary: TUI wrapper for CLI arguments
Project-URL: Homepage, https://git.sr.ht/~greenfoo/tuiargs
Project-URL: Issues, https://todo.sr.ht/~greenfoo/tuiargs
Author-email: Fernando Ramos <greenfoo@u92.eu>
License-File: LICENSE
Classifier: License :: OSI Approved :: GNU General Public License v3 (GPLv3)
Classifier: Operating System :: OS Independent
Classifier: Programming Language :: Python :: 3
Classifier: Topic :: Software Development :: User Interfaces
Requires-Python: >=3.7
